pipeless_agents_sdk/__init__.py
pipeless_agents_sdk/cloud.py
pipeless_agents_sdk-0.1.0.dist-info/METADATA
pipeless_agents_sdk-0.1.0.dist-info/WHEEL
pipeless_agents_sdk-0.1.0.dist-info/RECORD
