Metadata-Version: 2.1
Name: pipeless-agents-sdk
Version: 0.1.0
Summary: SDK to create applications based on Pipeless Agents
Home-page: https://agents.pipeless.ai
License: Apache-2.0
Author: Pipeless, Inc
Requires-Python: >=3.10,<4.0
Classifier: License :: OSI Approved :: Apache Software License
Classifier: Programming Language :: Python :: 3
Classifier: Programming Language :: Python :: 3.10
Classifier: Programming Language :: Python :: 3.11
Requires-Dist: kafka-python (>=2.0.2,<3.0.0)
